heath/__init__.py
heath/__init___test.py
heath/commands.py
heath/conftest.py
heath/py.typed
heath-0.4.1.dist-info/entry_points.txt
heath-0.4.1.dist-info/LICENSE.md
heath-0.4.1.dist-info/WHEEL
heath-0.4.1.dist-info/METADATA
heath-0.4.1.dist-info/RECORD
